src/GUI.py
src/__init__.py
src/analyze.py
src/layouts.py
src/log.py
src/output_dialog.py
src/page.py
src/types_supported.py
clarisse-0.0.3.dist-info/LICENSE
clarisse-0.0.3.dist-info/METADATA
clarisse-0.0.3.dist-info/WHEEL
clarisse-0.0.3.dist-info/top_level.txt
clarisse-0.0.3.dist-info/RECORD
