Metadata-Version: 2.1
Name: clarisse
Version: 0.0.3
Summary: A light-weighted GUI framework for Python programs.
Home-page: https://github.com/1MLightyears/clarisse
Author: Lightyears
Author-email: 1MLightyears@gmail.com
License: Apache 2.0
Platform: UNKNOWN
Classifier: Programming Language :: Python :: 3.9
Classifier: Operating System :: OS Independent
Classifier: Development Status :: 2 - Pre-Alpha
Classifier: License :: OSI Approved :: Apache Software License
Classifier: Natural Language :: English
Requires-Python: >=3.6
Requires-Dist: PySide2
